{
  "generated": "2026-03-06T00:39:40Z",
  "since": "2024-12-12",
  "until": "2024-12-12",
  "summary": {
    "total_commits": 1,
    "repos_active": 1,
    "files_changed": 1,
    "organs_touched": [
      "III"
    ]
  },
  "by_organ": {
    "III": {
      "name": "Ergon",
      "repos": {
        "anon-hookup-now": {
          "commits": [
            {
              "hash": "ebc5343",
              "date": "2024-12-12",
              "message": "GrindrPlus: Attempts to get unlimited VCs"
            }
          ],
          "files_changed": 1
        }
      }
    }
  }
}
