{
  "generated": "2026-03-06T00:39:41Z",
  "since": "2024-04-27",
  "until": "2024-04-27",
  "summary": {
    "total_commits": 5,
    "repos_active": 1,
    "files_changed": 37,
    "organs_touched": [
      "III"
    ]
  },
  "by_organ": {
    "III": {
      "name": "Ergon",
      "repos": {
        "anon-hookup-now": {
          "commits": [
            {
              "hash": "363bf68",
              "date": "2024-04-27",
              "message": "GrindrPlus: Add poundross to the contributors list"
            },
            {
              "hash": "966ab6f",
              "date": "2024-04-27",
              "message": "Location: Improve the `/save` command"
            },
            {
              "hash": "fc7411f",
              "date": "2024-04-27",
              "message": "ExpiringPhotos: Fix unlimited expiring photos"
            },
            {
              "hash": "9ea75b6",
              "date": "2024-04-27",
              "message": "FeatureGranting: Fix invalid method names"
            },
            {
              "hash": "7fc94f2",
              "date": "2024-04-27",
              "message": "GrindrPlus: Compatibility update for 24.4.0"
            }
          ],
          "files_changed": 37
        }
      }
    }
  }
}
