{
  "generated": "2026-03-06T00:39:40Z",
  "since": "2024-07-20",
  "until": "2024-07-20",
  "summary": {
    "total_commits": 2,
    "repos_active": 1,
    "files_changed": 0,
    "organs_touched": [
      "III"
    ]
  },
  "by_organ": {
    "III": {
      "name": "Ergon",
      "repos": {
        "anon-hookup-now": {
          "commits": [
            {
              "hash": "2a795d1",
              "date": "2024-07-20",
              "message": "GrindrPlus: Fix send video once for all"
            },
            {
              "hash": "16b6689",
              "date": "2024-07-20",
              "message": "GrindrPlus: Long press to copy ID with spacing"
            }
          ],
          "files_changed": 0
        }
      }
    }
  }
}
