{
  "generated": "2026-03-06T00:39:40Z",
  "since": "2024-09-15",
  "until": "2024-09-15",
  "summary": {
    "total_commits": 2,
    "repos_active": 1,
    "files_changed": 8,
    "organs_touched": [
      "III"
    ]
  },
  "by_organ": {
    "III": {
      "name": "Ergon",
      "repos": {
        "anon-hookup-now": {
          "commits": [
            {
              "hash": "37339b2",
              "date": "2024-09-15",
              "message": "GrindrPlus: Add initial build workflow"
            },
            {
              "hash": "0ecf188",
              "date": "2024-09-15",
              "message": "GrindrPlus: Append commit hash to `versionName`"
            }
          ],
          "files_changed": 8
        }
      }
    }
  }
}
