{
  "generated": "2026-03-06T00:39:27Z",
  "since": "2026-03-01",
  "until": "2026-03-01",
  "summary": {
    "total_commits": 5,
    "repos_active": 5,
    "files_changed": 234,
    "organs_touched": [
      "I",
      "III",
      "META",
      "Personal"
    ]
  },
  "by_organ": {
    "Personal": {
      "name": "Personal",
      "repos": {
        "application-pipeline": {
          "commits": [
            {
              "hash": "7c97c2a",
              "date": "2026-03-01",
              "message": "chore: stage and commit all changes"
            }
          ],
          "files_changed": 230
        }
      }
    },
    "META": {
      "name": "Meta",
      "repos": {
        "organvm-corpvs-testamentvm": {
          "commits": [
            {
              "hash": "569e7e6",
              "date": "2026-03-01",
              "message": "chore(soak): daily snapshot 2026-03-01"
            }
          ],
          "files_changed": 1
        }
      }
    },
    "I": {
      "name": "Theoria",
      "repos": {
        "organvm-i-theoria": {
          "commits": [
            {
              "hash": "c7a2366",
              "date": "2026-03-01",
              "message": "Stage and commit all changes"
            }
          ],
          "files_changed": 1
        }
      }
    },
    "III": {
      "name": "Ergon",
      "repos": {
        "organvm-corpvs-testamentvm": {
          "commits": [
            {
              "hash": "569e7e6",
              "date": "2026-03-01",
              "message": "chore(soak): daily snapshot 2026-03-01"
            }
          ],
          "files_changed": 1
        },
        "organvm-i-theoria--superproject": {
          "commits": [
            {
              "hash": "c7a2366",
              "date": "2026-03-01",
              "message": "Stage and commit all changes"
            }
          ],
          "files_changed": 1
        }
      }
    }
  }
}
